deepeye/__init__.py
deepeye/srgan_wrapper.py
deepeye/models/__init__.py
deepeye/models/bsrgan_network_rrdbnet.py
deepeye/models/esrgan_network_rrdbnet.py
deepeye/models/payload.py
deepeye/utils/__init__.py
deepeye/utils/logging.py
deepeye/utils/singleton.py
deepeye/utils/utils_image.py
deepeye-0.1.14.dist-info/licenses/LICENSE
deepeye-0.1.14.dist-info/METADATA
deepeye-0.1.14.dist-info/WHEEL
deepeye-0.1.14.dist-info/top_level.txt
deepeye-0.1.14.dist-info/RECORD
